odoo/addons/account_banking_ach_credit_transfer/README.rst
odoo/addons/account_banking_ach_credit_transfer/__init__.py
odoo/addons/account_banking_ach_credit_transfer/__manifest__.py
odoo/addons/account_banking_ach_credit_transfer/post_install.py
odoo/addons/account_banking_ach_credit_transfer/data/account_payment_method.xml
odoo/addons/account_banking_ach_credit_transfer/demo/ach_credit_transfer_demo.xml
odoo/addons/account_banking_ach_credit_transfer/i18n/account_banking_ach_credit_transfer.pot
odoo/addons/account_banking_ach_credit_transfer/models/__init__.py
odoo/addons/account_banking_ach_credit_transfer/models/account_payment_order.py
odoo/addons/account_banking_ach_credit_transfer/readme/CONFIGURE.rst
odoo/addons/account_banking_ach_credit_transfer/readme/CONTRIBUTORS.rst
odoo/addons/account_banking_ach_credit_transfer/readme/DESCRIPTION.rst
odoo/addons/account_banking_ach_credit_transfer/readme/INSTALL.rst
odoo/addons/account_banking_ach_credit_transfer/static/description/icon.png
odoo/addons/account_banking_ach_credit_transfer/static/description/index.html
odoo/addons/account_banking_ach_credit_transfer/views/account_payment_order.xml
odoo12_addon_account_banking_ach_credit_transfer-12.0.1.0.0.99.dev4.dist-info/METADATA
odoo12_addon_account_banking_ach_credit_transfer-12.0.1.0.0.99.dev4.dist-info/WHEEL
odoo12_addon_account_banking_ach_credit_transfer-12.0.1.0.0.99.dev4.dist-info/top_level.txt
odoo12_addon_account_banking_ach_credit_transfer-12.0.1.0.0.99.dev4.dist-info/RECORD
